Workbook

Sheet January
A1: Smith Family Budget
A3: Income | B3: Source | D3: Planned | E3: Actual | F3: Difference
B4: Mr. Smith Paycheck | D4: 3800 | E4: 3800 | F4: =E4-D4 -> 0
B5: Mrs. Smith Paycheck | D5: 1400 | E5: 1400 | F5: =E5-D5 -> 0
B6: Door Dash | D6: 300 | E6: 375 | F6: =E6-D6 -> 75
C7: Total | D7: =D6+D5+D4 -> 5500 | E7: =E6+E5+E4 -> 5575 | F7: =E7-D7 -> 75
G9: Total | H9: =F7+E32 -> -225
A11: Expenses | B11: Expense | C11: Planned | D11: Actual | E11: Difference | F11: Percentage
B12: Housing | C12: 1700 | D12: 1700 | E12: =C12-D12 -> 0 | F12: =D12/D32 -> 0.29310345
B13: Groceries | C13: 350 | D13: 362 | E13: =C13-D13 -> -12 | F13: =D13/D32 -> 0.062413793
B14: Telephone | C14: 275 | D14: 275 | E14: =C14-D14 -> 0 | F14: =D14/D32 -> 0.047413793
B15: Electric/ Gas | C15: 175 | D15: 78 | E15: =C15-D15 -> 97 | F15: =D15/D32 -> 0.013448276
B16: Water/ Seewer/ Trash | C16: 52 | D16: 54 | E16: =C16-D16 -> -2 | F16: =D16/D32 -> 0.0093103448
B17: Cable TV | C17: 115 | D17: 115 | E17: =C17-D17 -> 0 | F17: =D17/D32 -> 0.019827586
B18: Tuition | C18: 500 | D18: 475 | E18: =C18-D18 -> 25 | F18: =D18/D32 -> 0.081896552
B19: Internet | C19: 60 | D19: 60 | E19: =C19-D19 -> 0 | F19: =D19/D32 -> 0.010344828
B20: Maintenance/ Repairs | C20: 0 | D20: 25 | E20: =C20-D20 -> -25 | F20: =D20/D32 -> 0.0043103448
B21: Dining Out | C21: 200 | D21: 210 | E21: =C21-D21 -> -10 | F21: =D21/D32 -> 0.036206897
B22: Pets | C22: 50 | D22: 80 | E22: =C22-D22 -> -30 | F22: =D22/D32 -> 0.013793103
B23: Trasnportaion | C23: 300 | D23: 260 | E23: =C23-D23 -> 40 | F23: =D23/D32 -> 0.044827586
B24: Personal Care | C24: 80 | D24: 65 | E24: =C24-D24 -> 15 | F24: =D24/D32 -> 0.011206897
B25: Insurance | C25: 175 | D25: 255 | E25: =C25-D25 -> -80 | F25: =D25/D32 -> 0.043965517
B26: Credit Cards | C26: 425 | D26: 575 | E26: =C26-D26 -> -150 | F26: =D26/D32 -> 0.099137931
B27: Loans | C27: 0 | D27: 0 | E27: =C27-D27 -> 0 | F27: =D27/D32 -> 0
B28: Taxes | C28: 0 | D28: 350 | E28: =C28-D28 -> -350 | F28: =D28/D32 -> 0.060344828
B29: Gifts/ Charity | C29: 75 | D29: 125 | E29: =C29-D29 -> -50 | F29: =D29/D32 -> 0.021551724
B30: Savings | C30: 950 | D30: 736 | E30: =C30-D30 -> 214 | F30: =D30/D32 -> 0.12689655
B31: Other | C31: 18 | D31: 0 | E31: =C31-D31 -> 18 | F31: =D31/D32 -> 0
B32: Total | C32: =SUM(C12:C31) -> 5500 | D32: =SUM(D12:D31) -> 5800 | E32: =C32-D32 -> -300 | F32: =SUM(F12:F31) -> 1

Sheet February
A1: Smith Family Budget
A3: Income | B3: Source | D3: Planned | E3: Actual | F3: Difference
B4: Mr. Smith Paycheck | D4: 3800 | E4: 3800 | F4: =E4-D4 -> 0
B5: Mrs. Smith Paycheck | D5: 1400 | E5: 1400 | F5: =E5-D5 -> 0
B6: Door Dash | D6: 300 | E6: 375 | F6: =E6-D6 -> 75
C7: Total | D7: =D6+D5+D4 -> 5500 | E7: =E6+E5+E4 -> 5575 | F7: =E7-D7 -> 75
G9: Total | H9: =F7+E32 -> -225
A11: Expenses | B11: Expense | C11: Planned | D11: Actual | E11: Difference | F11: Percentage
B12: Housing | C12: 1700 | D12: 1700 | E12: =C12-D12 -> 0 | F12: =D12/D32 -> 0.29310345
B13: Groceries | C13: 350 | D13: 362 | E13: =C13-D13 -> -12 | F13: =D13/D32 -> 0.062413793
B14: Telephone | C14: 275 | D14: 275 | E14: =C14-D14 -> 0 | F14: =D14/D32 -> 0.047413793
B15: Electric/ Gas | C15: 175 | D15: 78 | E15: =C15-D15 -> 97 | F15: =D15/D32 -> 0.013448276
B16: Water/ Seewer/ Trash | C16: 52 | D16: 54 | E16: =C16-D16 -> -2 | F16: =D16/D32 -> 0.0093103448
B17: Cable TV | C17: 115 | D17: 115 | E17: =C17-D17 -> 0 | F17: =D17/D32 -> 0.019827586
B18: Tuition | C18: 500 | D18: 475 | E18: =C18-D18 -> 25 | F18: =D18/D32 -> 0.081896552
B19: Internet | C19: 60 | D19: 60 | E19: =C19-D19 -> 0 | F19: =D19/D32 -> 0.010344828
B20: Maintenance/ Repairs | C20: 0 | D20: 25 | E20: =C20-D20 -> -25 | F20: =D20/D32 -> 0.0043103448
B21: Dining Out | C21: 200 | D21: 210 | E21: =C21-D21 -> -10 | F21: =D21/D32 -> 0.036206897
B22: Pets | C22: 50 | D22: 80 | E22: =C22-D22 -> -30 | F22: =D22/D32 -> 0.013793103
B23: Trasnportaion | C23: 300 | D23: 260 | E23: =C23-D23 -> 40 | F23: =D23/D32 -> 0.044827586
B24: Personal Care | C24: 80 | D24: 65 | E24: =C24-D24 -> 15 | F24: =D24/D32 -> 0.011206897
B25: Insurance | C25: 175 | D25: 255 | E25: =C25-D25 -> -80 | F25: =D25/D32 -> 0.043965517
B26: Credit Cards | C26: 425 | D26: 575 | E26: =C26-D26 -> -150 | F26: =D26/D32 -> 0.099137931
B27: Loans | C27: 0 | D27: 0 | E27: =C27-D27 -> 0 | F27: =D27/D32 -> 0
B28: Taxes | C28: 0 | D28: 350 | E28: =C28-D28 -> -350 | F28: =D28/D32 -> 0.060344828
B29: Gifts/ Charity | C29: 75 | D29: 125 | E29: =C29-D29 -> -50 | F29: =D29/D32 -> 0.021551724
B30: Savings | C30: 950 | D30: 736 | E30: =C30-D30 -> 214 | F30: =D30/D32 -> 0.12689655
B31: Other | C31: 18 | D31: 0 | E31: =C31-D31 -> 18 | F31: =D31/D32 -> 0
B32: Total | C32: =SUM(C12:C31) -> 5500 | D32: =SUM(D12:D31) -> 5800 | E32: =C32-D32 -> -300 | F32: =SUM(F12:F31) -> 1

Sheet March
A1: Smith Family Budget
A3: Income | B3: Source | D3: Planned | E3: Actual | F3: Difference
B4: Mr. Smith Paycheck | D4: 3800 | E4: 3800 | F4: =E4-D4 -> 0
B5: Mrs. Smith Paycheck | D5: 1400 | E5: 1400 | F5: =E5-D5 -> 0
B6: Door Dash | D6: 300 | E6: 375 | F6: =E6-D6 -> 75
C7: Total | D7: =D6+D5+D4 -> 5500 | E7: =E6+E5+E4 -> 5575 | F7: =E7-D7 -> 75
G9: Total | H9: =F7+E32 -> -225
A11: Expenses | B11: Expense | C11: Planned | D11: Actual | E11: Difference | F11: Percentage
B12: Housing | C12: 1700 | D12: 1700 | E12: =C12-D12 -> 0 | F12: =D12/D32 -> 0.29310345
B13: Groceries | C13: 350 | D13: 362 | E13: =C13-D13 -> -12 | F13: =D13/D32 -> 0.062413793
B14: Telephone | C14: 275 | D14: 275 | E14: =C14-D14 -> 0 | F14: =D14/D32 -> 0.047413793
B15: Electric/ Gas | C15: 175 | D15: 78 | E15: =C15-D15 -> 97 | F15: =D15/D32 -> 0.013448276
B16: Water/ Seewer/ Trash | C16: 52 | D16: 54 | E16: =C16-D16 -> -2 | F16: =D16/D32 -> 0.0093103448
B17: Cable TV | C17: 115 | D17: 115 | E17: =C17-D17 -> 0 | F17: =D17/D32 -> 0.019827586
B18: Tuition | C18: 500 | D18: 475 | E18: =C18-D18 -> 25 | F18: =D18/D32 -> 0.081896552
B19: Internet | C19: 60 | D19: 60 | E19: =C19-D19 -> 0 | F19: =D19/D32 -> 0.010344828
B20: Maintenance/ Repairs | C20: 0 | D20: 25 | E20: =C20-D20 -> -25 | F20: =D20/D32 -> 0.0043103448
B21: Dining Out | C21: 200 | D21: 210 | E21: =C21-D21 -> -10 | F21: =D21/D32 -> 0.036206897
B22: Pets | C22: 50 | D22: 80 | E22: =C22-D22 -> -30 | F22: =D22/D32 -> 0.013793103
B23: Trasnportaion | C23: 300 | D23: 260 | E23: =C23-D23 -> 40 | F23: =D23/D32 -> 0.044827586
B24: Personal Care | C24: 80 | D24: 65 | E24: =C24-D24 -> 15 | F24: =D24/D32 -> 0.011206897
B25: Insurance | C25: 175 | D25: 255 | E25: =C25-D25 -> -80 | F25: =D25/D32 -> 0.043965517
B26: Credit Cards | C26: 425 | D26: 575 | E26: =C26-D26 -> -150 | F26: =D26/D32 -> 0.099137931
B27: Loans | C27: 0 | D27: 0 | E27: =C27-D27 -> 0 | F27: =D27/D32 -> 0
B28: Taxes | C28: 0 | D28: 350 | E28: =C28-D28 -> -350 | F28: =D28/D32 -> 0.060344828
B29: Gifts/ Charity | C29: 75 | D29: 125 | E29: =C29-D29 -> -50 | F29: =D29/D32 -> 0.021551724
B30: Savings | C30: 950 | D30: 736 | E30: =C30-D30 -> 214 | F30: =D30/D32 -> 0.12689655
B31: Other | C31: 18 | D31: 0 | E31: =C31-D31 -> 18 | F31: =D31/D32 -> 0
B32: Total | C32: =SUM(C12:C31) -> 5500 | D32: =SUM(D12:D31) -> 5800 | E32: =C32-D32 -> -300 | F32: =SUM(F12:F31) -> 1

Sheet April
A1: Smith Family Budget
A3: Income | B3: Source | D3: Planned | E3: Actual | F3: Difference
B4: Mr. Smith Paycheck | D4: 3800 | E4: 3800 | F4: =E4-D4 -> 0
B5: Mrs. Smith Paycheck | D5: 1400 | E5: 1400 | F5: =E5-D5 -> 0
B6: Door Dash | D6: 300 | E6: 375 | F6: =E6-D6 -> 75
C7: Total | D7: =D6+D5+D4 -> 5500 | E7: =E6+E5+E4 -> 5575 | F7: =E7-D7 -> 75
G9: Total | H9: =F7+E32 -> -225
A11: Expenses | B11: Expense | C11: Planned | D11: Actual | E11: Difference | F11: Percentage
B12: Housing | C12: 1700 | D12: 1700 | E12: =C12-D12 -> 0 | F12: =D12/D32 -> 0.29310345
B13: Groceries | C13: 350 | D13: 362 | E13: =C13-D13 -> -12 | F13: =D13/D32 -> 0.062413793
B14: Telephone | C14: 275 | D14: 275 | E14: =C14-D14 -> 0 | F14: =D14/D32 -> 0.047413793
B15: Electric/ Gas | C15: 175 | D15: 78 | E15: =C15-D15 -> 97 | F15: =D15/D32 -> 0.013448276
B16: Water/ Seewer/ Trash | C16: 52 | D16: 54 | E16: =C16-D16 -> -2 | F16: =D16/D32 -> 0.0093103448
B17: Cable TV | C17: 115 | D17: 115 | E17: =C17-D17 -> 0 | F17: =D17/D32 -> 0.019827586
B18: Tuition | C18: 500 | D18: 475 | E18: =C18-D18 -> 25 | F18: =D18/D32 -> 0.081896552
B19: Internet | C19: 60 | D19: 60 | E19: =C19-D19 -> 0 | F19: =D19/D32 -> 0.010344828
B20: Maintenance/ Repairs | C20: 0 | D20: 25 | E20: =C20-D20 -> -25 | F20: =D20/D32 -> 0.0043103448
B21: Dining Out | C21: 200 | D21: 210 | E21: =C21-D21 -> -10 | F21: =D21/D32 -> 0.036206897
B22: Pets | C22: 50 | D22: 80 | E22: =C22-D22 -> -30 | F22: =D22/D32 -> 0.013793103
B23: Trasnportaion | C23: 300 | D23: 260 | E23: =C23-D23 -> 40 | F23: =D23/D32 -> 0.044827586
B24: Personal Care | C24: 80 | D24: 65 | E24: =C24-D24 -> 15 | F24: =D24/D32 -> 0.011206897
B25: Insurance | C25: 175 | D25: 255 | E25: =C25-D25 -> -80 | F25: =D25/D32 -> 0.043965517
B26: Credit Cards | C26: 425 | D26: 575 | E26: =C26-D26 -> -150 | F26: =D26/D32 -> 0.099137931
B27: Loans | C27: 0 | D27: 0 | E27: =C27-D27 -> 0 | F27: =D27/D32 -> 0
B28: Taxes | C28: 0 | D28: 350 | E28: =C28-D28 -> -350 | F28: =D28/D32 -> 0.060344828
B29: Gifts/ Charity | C29: 75 | D29: 125 | E29: =C29-D29 -> -50 | F29: =D29/D32 -> 0.021551724
B30: Savings | C30: 950 | D30: 736 | E30: =C30-D30 -> 214 | F30: =D30/D32 -> 0.12689655
B31: Other | C31: 18 | D31: 0 | E31: =C31-D31 -> 18 | F31: =D31/D32 -> 0
B32: Total | C32: =SUM(C12:C31) -> 5500 | D32: =SUM(D12:D31) -> 5800 | E32: =C32-D32 -> -300 | F32: =SUM(F12:F31) -> 1

Sheet May
A1: Smith Family Budget
A3: Income | B3: Source | D3: Planned | E3: Actual | F3: Difference
B4: Mr. Smith Paycheck | D4: 3800 | E4: 3800 | F4: =E4-D4 -> 0
B5: Mrs. Smith Paycheck | D5: 1400 | E5: 1400 | F5: =E5-D5 -> 0
B6: Door Dash | D6: 300 | E6: 375 | F6: =E6-D6 -> 75
C7: Total | D7: =D6+D5+D4 -> 5500 | E7: =E6+E5+E4 -> 5575 | F7: =E7-D7 -> 75
G9: Total | H9: =F7+E32 -> -225
A11: Expenses | B11: Expense | C11: Planned | D11: Actual | E11: Difference | F11: Percentage
B12: Housing | C12: 1700 | D12: 1700 | E12: =C12-D12 -> 0 | F12: =D12/D32 -> 0.29310345
B13: Groceries | C13: 350 | D13: 362 | E13: =C13-D13 -> -12 | F13: =D13/D32 -> 0.062413793
B14: Telephone | C14: 275 | D14: 275 | E14: =C14-D14 -> 0 | F14: =D14/D32 -> 0.047413793
B15: Electric/ Gas | C15: 175 | D15: 78 | E15: =C15-D15 -> 97 | F15: =D15/D32 -> 0.013448276
B16: Water/ Seewer/ Trash | C16: 52 | D16: 54 | E16: =C16-D16 -> -2 | F16: =D16/D32 -> 0.0093103448
B17: Cable TV | C17: 115 | D17: 115 | E17: =C17-D17 -> 0 | F17: =D17/D32 -> 0.019827586
B18: Tuition | C18: 500 | D18: 475 | E18: =C18-D18 -> 25 | F18: =D18/D32 -> 0.081896552
B19: Internet | C19: 60 | D19: 60 | E19: =C19-D19 -> 0 | F19: =D19/D32 -> 0.010344828
B20: Maintenance/ Repairs | C20: 0 | D20: 25 | E20: =C20-D20 -> -25 | F20: =D20/D32 -> 0.0043103448
B21: Dining Out | C21: 200 | D21: 210 | E21: =C21-D21 -> -10 | F21: =D21/D32 -> 0.036206897
B22: Pets | C22: 50 | D22: 80 | E22: =C22-D22 -> -30 | F22: =D22/D32 -> 0.013793103
B23: Trasnportaion | C23: 300 | D23: 260 | E23: =C23-D23 -> 40 | F23: =D23/D32 -> 0.044827586
B24: Personal Care | C24: 80 | D24: 65 | E24: =C24-D24 -> 15 | F24: =D24/D32 -> 0.011206897
B25: Insurance | C25: 175 | D25: 255 | E25: =C25-D25 -> -80 | F25: =D25/D32 -> 0.043965517
B26: Credit Cards | C26: 425 | D26: 575 | E26: =C26-D26 -> -150 | F26: =D26/D32 -> 0.099137931
B27: Loans | C27: 0 | D27: 0 | E27: =C27-D27 -> 0 | F27: =D27/D32 -> 0
B28: Taxes | C28: 0 | D28: 350 | E28: =C28-D28 -> -350 | F28: =D28/D32 -> 0.060344828
B29: Gifts/ Charity | C29: 75 | D29: 125 | E29: =C29-D29 -> -50 | F29: =D29/D32 -> 0.021551724
B30: Savings | C30: 950 | D30: 736 | E30: =C30-D30 -> 214 | F30: =D30/D32 -> 0.12689655
B31: Other | C31: 18 | D31: 0 | E31: =C31-D31 -> 18 | F31: =D31/D32 -> 0
B32: Total | C32: =SUM(C12:C31) -> 5500 | D32: =SUM(D12:D31) -> 5800 | E32: =C32-D32 -> -300 | F32: =SUM(F12:F31) -> 1

Sheet June
A1: Smith Family Budget
A3: Income | B3: Source | D3: Planned | E3: Actual | F3: Difference
B4: Mr. Smith Paycheck | D4: 3800 | E4: 3800 | F4: =E4-D4 -> 0
B5: Mrs. Smith Paycheck | D5: 1400 | E5: 1400 | F5: =E5-D5 -> 0
B6: Door Dash | D6: 300 | E6: 375 | F6: =E6-D6 -> 75
C7: Total | D7: =D6+D5+D4 -> 5500 | E7: =E6+E5+E4 -> 5575 | F7: =E7-D7 -> 75
G9: Total | H9: =F7+E32 -> -225
A11: Expenses | B11: Expense | C11: Planned | D11: Actual | E11: Difference | F11: Percentage
B12: Housing | C12: 1700 | D12: 1700 | E12: =C12-D12 -> 0 | F12: =D12/D32 -> 0.29310345
B13: Groceries | C13: 350 | D13: 362 | E13: =C13-D13 -> -12 | F13: =D13/D32 -> 0.062413793
B14: Telephone | C14: 275 | D14: 275 | E14: =C14-D14 -> 0 | F14: =D14/D32 -> 0.047413793
B15: Electric/ Gas | C15: 175 | D15: 78 | E15: =C15-D15 -> 97 | F15: =D15/D32 -> 0.013448276
B16: Water/ Seewer/ Trash | C16: 52 | D16: 54 | E16: =C16-D16 -> -2 | F16: =D16/D32 -> 0.0093103448
B17: Cable TV | C17: 115 | D17: 115 | E17: =C17-D17 -> 0 | F17: =D17/D32 -> 0.019827586
B18: Tuition | C18: 500 | D18: 475 | E18: =C18-D18 -> 25 | F18: =D18/D32 -> 0.081896552
B19: Internet | C19: 60 | D19: 60 | E19: =C19-D19 -> 0 | F19: =D19/D32 -> 0.010344828
B20: Maintenance/ Repairs | C20: 0 | D20: 25 | E20: =C20-D20 -> -25 | F20: =D20/D32 -> 0.0043103448
B21: Dining Out | C21: 200 | D21: 210 | E21: =C21-D21 -> -10 | F21: =D21/D32 -> 0.036206897
B22: Pets | C22: 50 | D22: 80 | E22: =C22-D22 -> -30 | F22: =D22/D32 -> 0.013793103
B23: Trasnportaion | C23: 300 | D23: 260 | E23: =C23-D23 -> 40 | F23: =D23/D32 -> 0.044827586
B24: Personal Care | C24: 80 | D24: 65 | E24: =C24-D24 -> 15 | F24: =D24/D32 -> 0.011206897
B25: Insurance | C25: 175 | D25: 255 | E25: =C25-D25 -> -80 | F25: =D25/D32 -> 0.043965517
B26: Credit Cards | C26: 425 | D26: 575 | E26: =C26-D26 -> -150 | F26: =D26/D32 -> 0.099137931
B27: Loans | C27: 0 | D27: 0 | E27: =C27-D27 -> 0 | F27: =D27/D32 -> 0
B28: Taxes | C28: 0 | D28: 350 | E28: =C28-D28 -> -350 | F28: =D28/D32 -> 0.060344828
B29: Gifts/ Charity | C29: 75 | D29: 125 | E29: =C29-D29 -> -50 | F29: =D29/D32 -> 0.021551724
B30: Savings | C30: 950 | D30: 736 | E30: =C30-D30 -> 214 | F30: =D30/D32 -> 0.12689655
B31: Other | C31: 18 | D31: 0 | E31: =C31-D31 -> 18 | F31: =D31/D32 -> 0
B32: Total | C32: =SUM(C12:C31) -> 5500 | D32: =SUM(D12:D31) -> 5800 | E32: =C32-D32 -> -300 | F32: =SUM(F12:F31) -> 1

Sheet July
A1: Smith Family Budget
A3: Income | B3: Source | D3: Planned | E3: Actual | F3: Difference
B4: Mr. Smith Paycheck | D4: 3800 | E4: 3800 | F4: =E4-D4 -> 0
B5: Mrs. Smith Paycheck | D5: 1400 | E5: 1400 | F5: =E5-D5 -> 0
B6: Door Dash | D6: 300 | E6: 375 | F6: =E6-D6 -> 75
C7: Total | D7: =D6+D5+D4 -> 5500 | E7: =E6+E5+E4 -> 5575 | F7: =E7-D7 -> 75
G9: Total | H9: =F7+E32 -> -225
A11: Expenses | B11: Expense | C11: Planned | D11: Actual | E11: Difference | F11: Percentage
B12: Housing | C12: 1700 | D12: 1700 | E12: =C12-D12 -> 0 | F12: =D12/D32 -> 0.29310345
B13: Groceries | C13: 350 | D13: 362 | E13: =C13-D13 -> -12 | F13: =D13/D32 -> 0.062413793
B14: Telephone | C14: 275 | D14: 275 | E14: =C14-D14 -> 0 | F14: =D14/D32 -> 0.047413793
B15: Electric/ Gas | C15: 175 | D15: 78 | E15: =C15-D15 -> 97 | F15: =D15/D32 -> 0.013448276
B16: Water/ Seewer/ Trash | C16: 52 | D16: 54 | E16: =C16-D16 -> -2 | F16: =D16/D32 -> 0.0093103448
B17: Cable TV | C17: 115 | D17: 115 | E17: =C17-D17 -> 0 | F17: =D17/D32 -> 0.019827586
B18: Tuition | C18: 500 | D18: 475 | E18: =C18-D18 -> 25 | F18: =D18/D32 -> 0.081896552
B19: Internet | C19: 60 | D19: 60 | E19: =C19-D19 -> 0 | F19: =D19/D32 -> 0.010344828
B20: Maintenance/ Repairs | C20: 0 | D20: 25 | E20: =C20-D20 -> -25 | F20: =D20/D32 -> 0.0043103448
B21: Dining Out | C21: 200 | D21: 210 | E21: =C21-D21 -> -10 | F21: =D21/D32 -> 0.036206897
B22: Pets | C22: 50 | D22: 80 | E22: =C22-D22 -> -30 | F22: =D22/D32 -> 0.013793103
B23: Trasnportaion | C23: 300 | D23: 260 | E23: =C23-D23 -> 40 | F23: =D23/D32 -> 0.044827586
B24: Personal Care | C24: 80 | D24: 65 | E24: =C24-D24 -> 15 | F24: =D24/D32 -> 0.011206897
B25: Insurance | C25: 175 | D25: 255 | E25: =C25-D25 -> -80 | F25: =D25/D32 -> 0.043965517
B26: Credit Cards | C26: 425 | D26: 575 | E26: =C26-D26 -> -150 | F26: =D26/D32 -> 0.099137931
B27: Loans | C27: 0 | D27: 0 | E27: =C27-D27 -> 0 | F27: =D27/D32 -> 0
B28: Taxes | C28: 0 | D28: 350 | E28: =C28-D28 -> -350 | F28: =D28/D32 -> 0.060344828
B29: Gifts/ Charity | C29: 75 | D29: 125 | E29: =C29-D29 -> -50 | F29: =D29/D32 -> 0.021551724
B30: Savings | C30: 950 | D30: 736 | E30: =C30-D30 -> 214 | F30: =D30/D32 -> 0.12689655
B31: Other | C31: 18 | D31: 0 | E31: =C31-D31 -> 18 | F31: =D31/D32 -> 0
B32: Total | C32: =SUM(C12:C31) -> 5500 | D32: =SUM(D12:D31) -> 5800 | E32: =C32-D32 -> -300 | F32: =SUM(F12:F31) -> 1

Sheet August
A1: Smith Family Budget
A3: Income | B3: Source | D3: Planned | E3: Actual | F3: Difference
B4: Mr. Smith Paycheck | D4: 3800 | E4: 3800 | F4: =E4-D4 -> 0
B5: Mrs. Smith Paycheck | D5: 1400 | E5: 1400 | F5: =E5-D5 -> 0
B6: Door Dash | D6: 300 | E6: 375 | F6: =E6-D6 -> 75
C7: Total | D7: =D6+D5+D4 -> 5500 | E7: =E6+E5+E4 -> 5575 | F7: =E7-D7 -> 75
G9: Total | H9: =F7+E32 -> -225
A11: Expenses | B11: Expense | C11: Planned | D11: Actual | E11: Difference | F11: Percentage
B12: Housing | C12: 1700 | D12: 1700 | E12: =C12-D12 -> 0 | F12: =D12/D32 -> 0.29310345
B13: Groceries | C13: 350 | D13: 362 | E13: =C13-D13 -> -12 | F13: =D13/D32 -> 0.062413793
B14: Telephone | C14: 275 | D14: 275 | E14: =C14-D14 -> 0 | F14: =D14/D32 -> 0.047413793
B15: Electric/ Gas | C15: 175 | D15: 78 | E15: =C15-D15 -> 97 | F15: =D15/D32 -> 0.013448276
B16: Water/ Seewer/ Trash | C16: 52 | D16: 54 | E16: =C16-D16 -> -2 | F16: =D16/D32 -> 0.0093103448
B17: Cable TV | C17: 115 | D17: 115 | E17: =C17-D17 -> 0 | F17: =D17/D32 -> 0.019827586
B18: Tuition | C18: 500 | D18: 475 | E18: =C18-D18 -> 25 | F18: =D18/D32 -> 0.081896552
B19: Internet | C19: 60 | D19: 60 | E19: =C19-D19 -> 0 | F19: =D19/D32 -> 0.010344828
B20: Maintenance/ Repairs | C20: 0 | D20: 25 | E20: =C20-D20 -> -25 | F20: =D20/D32 -> 0.0043103448
B21: Dining Out | C21: 200 | D21: 210 | E21: =C21-D21 -> -10 | F21: =D21/D32 -> 0.036206897
B22: Pets | C22: 50 | D22: 80 | E22: =C22-D22 -> -30 | F22: =D22/D32 -> 0.013793103
B23: Trasnportaion | C23: 300 | D23: 260 | E23: =C23-D23 -> 40 | F23: =D23/D32 -> 0.044827586
B24: Personal Care | C24: 80 | D24: 65 | E24: =C24-D24 -> 15 | F24: =D24/D32 -> 0.011206897
B25: Insurance | C25: 175 | D25: 255 | E25: =C25-D25 -> -80 | F25: =D25/D32 -> 0.043965517
B26: Credit Cards | C26: 425 | D26: 575 | E26: =C26-D26 -> -150 | F26: =D26/D32 -> 0.099137931
B27: Loans | C27: 0 | D27: 0 | E27: =C27-D27 -> 0 | F27: =D27/D32 -> 0
B28: Taxes | C28: 0 | D28: 350 | E28: =C28-D28 -> -350 | F28: =D28/D32 -> 0.060344828
B29: Gifts/ Charity | C29: 75 | D29: 125 | E29: =C29-D29 -> -50 | F29: =D29/D32 -> 0.021551724
B30: Savings | C30: 950 | D30: 736 | E30: =C30-D30 -> 214 | F30: =D30/D32 -> 0.12689655
B31: Other | C31: 18 | D31: 0 | E31: =C31-D31 -> 18 | F31: =D31/D32 -> 0
B32: Total | C32: =SUM(C12:C31) -> 5500 | D32: =SUM(D12:D31) -> 5800 | E32: =C32-D32 -> -300 | F32: =SUM(F12:F31) -> 1

Sheet September
A1: Smith Family Budget
A3: Income | B3: Source | D3: Planned | E3: Actual | F3: Difference
B4: Mr. Smith Paycheck | D4: 3800 | E4: 3800 | F4: =E4-D4 -> 0
B5: Mrs. Smith Paycheck | D5: 1400 | E5: 1400 | F5: =E5-D5 -> 0
B6: Door Dash | D6: 300 | E6: 375 | F6: =E6-D6 -> 75
C7: Total | D7: =D6+D5+D4 -> 5500 | E7: =E6+E5+E4 -> 5575 | F7: =E7-D7 -> 75
G9: Total | H9: =F7+E32 -> -225
A11: Expenses | B11: Expense | C11: Planned | D11: Actual | E11: Difference | F11: Percentage
B12: Housing | C12: 1700 | D12: 1700 | E12: =C12-D12 -> 0 | F12: =D12/D32 -> 0.29310345
B13: Groceries | C13: 350 | D13: 362 | E13: =C13-D13 -> -12 | F13: =D13/D32 -> 0.062413793
B14: Telephone | C14: 275 | D14: 275 | E14: =C14-D14 -> 0 | F14: =D14/D32 -> 0.047413793
B15: Electric/ Gas | C15: 175 | D15: 78 | E15: =C15-D15 -> 97 | F15: =D15/D32 -> 0.013448276
B16: Water/ Seewer/ Trash | C16: 52 | D16: 54 | E16: =C16-D16 -> -2 | F16: =D16/D32 -> 0.0093103448
B17: Cable TV | C17: 115 | D17: 115 | E17: =C17-D17 -> 0 | F17: =D17/D32 -> 0.019827586
B18: Tuition | C18: 500 | D18: 475 | E18: =C18-D18 -> 25 | F18: =D18/D32 -> 0.081896552
B19: Internet | C19: 60 | D19: 60 | E19: =C19-D19 -> 0 | F19: =D19/D32 -> 0.010344828
B20: Maintenance/ Repairs | C20: 0 | D20: 25 | E20: =C20-D20 -> -25 | F20: =D20/D32 -> 0.0043103448
B21: Dining Out | C21: 200 | D21: 210 | E21: =C21-D21 -> -10 | F21: =D21/D32 -> 0.036206897
B22: Pets | C22: 50 | D22: 80 | E22: =C22-D22 -> -30 | F22: =D22/D32 -> 0.013793103
B23: Trasnportaion | C23: 300 | D23: 260 | E23: =C23-D23 -> 40 | F23: =D23/D32 -> 0.044827586
B24: Personal Care | C24: 80 | D24: 65 | E24: =C24-D24 -> 15 | F24: =D24/D32 -> 0.011206897
B25: Insurance | C25: 175 | D25: 255 | E25: =C25-D25 -> -80 | F25: =D25/D32 -> 0.043965517
B26: Credit Cards | C26: 425 | D26: 575 | E26: =C26-D26 -> -150 | F26: =D26/D32 -> 0.099137931
B27: Loans | C27: 0 | D27: 0 | E27: =C27-D27 -> 0 | F27: =D27/D32 -> 0
B28: Taxes | C28: 0 | D28: 350 | E28: =C28-D28 -> -350 | F28: =D28/D32 -> 0.060344828
B29: Gifts/ Charity | C29: 75 | D29: 125 | E29: =C29-D29 -> -50 | F29: =D29/D32 -> 0.021551724
B30: Savings | C30: 950 | D30: 736 | E30: =C30-D30 -> 214 | F30: =D30/D32 -> 0.12689655
B31: Other | C31: 18 | D31: 0 | E31: =C31-D31 -> 18 | F31: =D31/D32 -> 0
B32: Total | C32: =SUM(C12:C31) -> 5500 | D32: =SUM(D12:D31) -> 5800 | E32: =C32-D32 -> -300 | F32: =SUM(F12:F31) -> 1

Sheet October
A1: Smith Family Budget
A3: Income | B3: Source | D3: Planned | E3: Actual | F3: Difference
B4: Mr. Smith Paycheck | D4: 3800 | E4: 3800 | F4: =E4-D4 -> 0
B5: Mrs. Smith Paycheck | D5: 1400 | E5: 1400 | F5: =E5-D5 -> 0
B6: Door Dash | D6: 300 | E6: 375 | F6: =E6-D6 -> 75
C7: Total | D7: =D6+D5+D4 -> 5500 | E7: =E6+E5+E4 -> 5575 | F7: =E7-D7 -> 75
G9: Total | H9: =F7+E32 -> -225
A11: Expenses | B11: Expense | C11: Planned | D11: Actual | E11: Difference | F11: Percentage
B12: Housing | C12: 1700 | D12: 1700 | E12: =C12-D12 -> 0 | F12: =D12/D32 -> 0.29310345
B13: Groceries | C13: 350 | D13: 362 | E13: =C13-D13 -> -12 | F13: =D13/D32 -> 0.062413793
B14: Telephone | C14: 275 | D14: 275 | E14: =C14-D14 -> 0 | F14: =D14/D32 -> 0.047413793
B15: Electric/ Gas | C15: 175 | D15: 78 | E15: =C15-D15 -> 97 | F15: =D15/D32 -> 0.013448276
B16: Water/ Seewer/ Trash | C16: 52 | D16: 54 | E16: =C16-D16 -> -2 | F16: =D16/D32 -> 0.0093103448
B17: Cable TV | C17: 115 | D17: 115 | E17: =C17-D17 -> 0 | F17: =D17/D32 -> 0.019827586
B18: Tuition | C18: 500 | D18: 475 | E18: =C18-D18 -> 25 | F18: =D18/D32 -> 0.081896552
B19: Internet | C19: 60 | D19: 60 | E19: =C19-D19 -> 0 | F19: =D19/D32 -> 0.010344828
B20: Maintenance/ Repairs | C20: 0 | D20: 25 | E20: =C20-D20 -> -25 | F20: =D20/D32 -> 0.0043103448
B21: Dining Out | C21: 200 | D21: 210 | E21: =C21-D21 -> -10 | F21: =D21/D32 -> 0.036206897
B22: Pets | C22: 50 | D22: 80 | E22: =C22-D22 -> -30 | F22: =D22/D32 -> 0.013793103
B23: Trasnportaion | C23: 300 | D23: 260 | E23: =C23-D23 -> 40 | F23: =D23/D32 -> 0.044827586
B24: Personal Care | C24: 80 | D24: 65 | E24: =C24-D24 -> 15 | F24: =D24/D32 -> 0.011206897
B25: Insurance | C25: 175 | D25: 255 | E25: =C25-D25 -> -80 | F25: =D25/D32 -> 0.043965517
B26: Credit Cards | C26: 425 | D26: 575 | E26: =C26-D26 -> -150 | F26: =D26/D32 -> 0.099137931
B27: Loans | C27: 0 | D27: 0 | E27: =C27-D27 -> 0 | F27: =D27/D32 -> 0
B28: Taxes | C28: 0 | D28: 350 | E28: =C28-D28 -> -350 | F28: =D28/D32 -> 0.060344828
B29: Gifts/ Charity | C29: 75 | D29: 125 | E29: =C29-D29 -> -50 | F29: =D29/D32 -> 0.021551724
B30: Savings | C30: 950 | D30: 736 | E30: =C30-D30 -> 214 | F30: =D30/D32 -> 0.12689655
B31: Other | C31: 18 | D31: 0 | E31: =C31-D31 -> 18 | F31: =D31/D32 -> 0
B32: Total | C32: =SUM(C12:C31) -> 5500 | D32: =SUM(D12:D31) -> 5800 | E32: =C32-D32 -> -300 | F32: =SUM(F12:F31) -> 1

Sheet November
A1: Smith Family Budget
A3: Income | B3: Source | D3: Planned | E3: Actual | F3: Difference
B4: Mr. Smith Paycheck | D4: 3800 | E4: 3800 | F4: =E4-D4 -> 0
B5: Mrs. Smith Paycheck | D5: 1400 | E5: 1400 | F5: =E5-D5 -> 0
B6: Door Dash | D6: 300 | E6: 375 | F6: =E6-D6 -> 75
C7: Total | D7: =D6+D5+D4 -> 5500 | E7: =E6+E5+E4 -> 5575 | F7: =E7-D7 -> 75
G9: Total | H9: =F7+E32 -> -225
A11: Expenses | B11: Expense | C11: Planned | D11: Actual | E11: Difference | F11: Percentage
B12: Housing | C12: 1700 | D12: 1700 | E12: =C12-D12 -> 0 | F12: =D12/D32 -> 0.29310345
B13: Groceries | C13: 350 | D13: 362 | E13: =C13-D13 -> -12 | F13: =D13/D32 -> 0.062413793
B14: Telephone | C14: 275 | D14: 275 | E14: =C14-D14 -> 0 | F14: =D14/D32 -> 0.047413793
B15: Electric/ Gas | C15: 175 | D15: 78 | E15: =C15-D15 -> 97 | F15: =D15/D32 -> 0.013448276
B16: Water/ Seewer/ Trash | C16: 52 | D16: 54 | E16: =C16-D16 -> -2 | F16: =D16/D32 -> 0.0093103448
B17: Cable TV | C17: 115 | D17: 115 | E17: =C17-D17 -> 0 | F17: =D17/D32 -> 0.019827586
B18: Tuition | C18: 500 | D18: 475 | E18: =C18-D18 -> 25 | F18: =D18/D32 -> 0.081896552
B19: Internet | C19: 60 | D19: 60 | E19: =C19-D19 -> 0 | F19: =D19/D32 -> 0.010344828
B20: Maintenance/ Repairs | C20: 0 | D20: 25 | E20: =C20-D20 -> -25 | F20: =D20/D32 -> 0.0043103448
B21: Dining Out | C21: 200 | D21: 210 | E21: =C21-D21 -> -10 | F21: =D21/D32 -> 0.036206897
B22: Pets | C22: 50 | D22: 80 | E22: =C22-D22 -> -30 | F22: =D22/D32 -> 0.013793103
B23: Trasnportaion | C23: 300 | D23: 260 | E23: =C23-D23 -> 40 | F23: =D23/D32 -> 0.044827586
B24: Personal Care | C24: 80 | D24: 65 | E24: =C24-D24 -> 15 | F24: =D24/D32 -> 0.011206897
B25: Insurance | C25: 175 | D25: 255 | E25: =C25-D25 -> -80 | F25: =D25/D32 -> 0.043965517
B26: Credit Cards | C26: 425 | D26: 575 | E26: =C26-D26 -> -150 | F26: =D26/D32 -> 0.099137931
B27: Loans | C27: 0 | D27: 0 | E27: =C27-D27 -> 0 | F27: =D27/D32 -> 0
B28: Taxes | C28: 0 | D28: 350 | E28: =C28-D28 -> -350 | F28: =D28/D32 -> 0.060344828
B29: Gifts/ Charity | C29: 75 | D29: 125 | E29: =C29-D29 -> -50 | F29: =D29/D32 -> 0.021551724
B30: Savings | C30: 950 | D30: 736 | E30: =C30-D30 -> 214 | F30: =D30/D32 -> 0.12689655
B31: Other | C31: 18 | D31: 0 | E31: =C31-D31 -> 18 | F31: =D31/D32 -> 0
B32: Total | C32: =SUM(C12:C31) -> 5500 | D32: =SUM(D12:D31) -> 5800 | E32: =C32-D32 -> -300 | F32: =SUM(F12:F31) -> 1

Sheet December
A1: Smith Family Budget
A3: Income | B3: Source | D3: Planned | E3: Actual | F3: Difference
B4: Mr. Smith Paycheck | D4: 3800 | E4: 3800 | F4: =E4-D4 -> 0
B5: Mrs. Smith Paycheck | D5: 1400 | E5: 1400 | F5: =E5-D5 -> 0
B6: Door Dash | D6: 300 | E6: 375 | F6: =E6-D6 -> 75
C7: Total | D7: =D6+D5+D4 -> 5500 | E7: =E6+E5+E4 -> 5575 | F7: =E7-D7 -> 75
G9: Total | H9: =F7+E32 -> -225
A11: Expenses | B11: Expense | C11: Planned | D11: Actual | E11: Difference | F11: Percentage
B12: Housing | C12: 1700 | D12: 1700 | E12: =C12-D12 -> 0 | F12: =D12/D32 -> 0.29310345
B13: Groceries | C13: 350 | D13: 362 | E13: =C13-D13 -> -12 | F13: =D13/D32 -> 0.062413793
B14: Telephone | C14: 275 | D14: 275 | E14: =C14-D14 -> 0 | F14: =D14/D32 -> 0.047413793
B15: Electric/ Gas | C15: 175 | D15: 78 | E15: =C15-D15 -> 97 | F15: =D15/D32 -> 0.013448276
B16: Water/ Seewer/ Trash | C16: 52 | D16: 54 | E16: =C16-D16 -> -2 | F16: =D16/D32 -> 0.0093103448
B17: Cable TV | C17: 115 | D17: 115 | E17: =C17-D17 -> 0 | F17: =D17/D32 -> 0.019827586
B18: Tuition | C18: 500 | D18: 475 | E18: =C18-D18 -> 25 | F18: =D18/D32 -> 0.081896552
B19: Internet | C19: 60 | D19: 60 | E19: =C19-D19 -> 0 | F19: =D19/D32 -> 0.010344828
B20: Maintenance/ Repairs | C20: 0 | D20: 25 | E20: =C20-D20 -> -25 | F20: =D20/D32 -> 0.0043103448
B21: Dining Out | C21: 200 | D21: 210 | E21: =C21-D21 -> -10 | F21: =D21/D32 -> 0.036206897
B22: Pets | C22: 50 | D22: 80 | E22: =C22-D22 -> -30 | F22: =D22/D32 -> 0.013793103
B23: Trasnportaion | C23: 300 | D23: 260 | E23: =C23-D23 -> 40 | F23: =D23/D32 -> 0.044827586
B24: Personal Care | C24: 80 | D24: 65 | E24: =C24-D24 -> 15 | F24: =D24/D32 -> 0.011206897
B25: Insurance | C25: 175 | D25: 255 | E25: =C25-D25 -> -80 | F25: =D25/D32 -> 0.043965517
B26: Credit Cards | C26: 425 | D26: 575 | E26: =C26-D26 -> -150 | F26: =D26/D32 -> 0.099137931
B27: Loans | C27: 0 | D27: 0 | E27: =C27-D27 -> 0 | F27: =D27/D32 -> 0
B28: Taxes | C28: 0 | D28: 350 | E28: =C28-D28 -> -350 | F28: =D28/D32 -> 0.060344828
B29: Gifts/ Charity | C29: 75 | D29: 125 | E29: =C29-D29 -> -50 | F29: =D29/D32 -> 0.021551724
B30: Savings | C30: 950 | D30: 736 | E30: =C30-D30 -> 214 | F30: =D30/D32 -> 0.12689655
B31: Other | C31: 18 | D31: 0 | E31: =C31-D31 -> 18 | F31: =D31/D32 -> 0
B32: Total | C32: =SUM(C12:C31) -> 5500 | D32: =SUM(D12:D31) -> 5800 | E32: =C32-D32 -> -300 | F32: =SUM(F12:F31) -> 1

Sheet 2021
A1: Smith Family Budget
A3: Income | B3: Source | D3: Planned | E3: Actual | F3: Difference
B4: Mr. Smith Paycheck | D4: =December!D4+November!D4+October!D4+September!D4+August!D4+July!D4+June!D4+May!D4+April!D4+March!D4+February!D4+January!D4 -> 45600 | E4: =December!E4+November!E4+October!E4+September!E4+August!E4+July!E4+June!E4+May!E4+April!E4+March!E4+February!E4+January!E4 -> 45600 | F4: =E4-D4 -> 0
B5: Mrs. Smith Paycheck | D5: =December!D5+November!D5+October!D5+September!D5+August!D5+July!D5+June!D5+May!D5+April!D5+March!D5+February!D5+January!D5 -> 16800 | E5: =December!E5+November!E5+October!E5+September!E5+August!E5+July!E5+June!E5+May!E5+April!E5+March!E5+February!E5+January!E5 -> 16800 | F5: =E5-D5 -> 0
B6: Door Dash | D6: =December!D6+November!D6+October!D6+September!D6+August!D6+July!D6+June!D6+May!D6+April!D6+March!D6+February!D6+January!D6 -> 3600 | E6: =December!E6+November!E6+October!E6+September!E6+August!E6+July!E6+June!E6+May!E6+April!E6+March!E6+February!E6+January!E6 -> 4500 | F6: =E6-D6 -> 900
C7: Total | D7: =D6+D5+D4 -> 66000 | E7: =E6+E5+E4 -> 66900 | F7: =E7-D7 -> 900
G9: Total | H9: =F7+E32 -> -2700
A11: Expenses | B11: Expense | C11: Planned | D11: Actual | E11: Difference | F11: Percentage
B12: Housing | C12: =December!C12+November!C12+October!C12+September!C12+August!C12+July!C12+June!C12+May!C12+April!C12+March!C12+February!C12+January!C12 -> 20400 | D12: =December!D12+November!D12+October!D12+September!D12+August!D12+July!D12+June!D12+May!D12+April!D12+March!D12+February!D12+January!D12 -> 20400 | E12: =C12-D12 -> 0 | F12: =D12/D32 -> 0.29310345
B13: Groceries | C13: =December!C13+November!C13+October!C13+September!C13+August!C13+July!C13+June!C13+May!C13+April!C13+March!C13+February!C13+January!C13 -> 4200 | D13: =December!D13+November!D13+October!D13+September!D13+August!D13+July!D13+June!D13+May!D13+April!D13+March!D13+February!D13+January!D13 -> 4344 | E13: =C13-D13 -> -144 | F13: =D13/D32 -> 0.062413793
B14: Telephone | C14: =December!C14+November!C14+October!C14+September!C14+August!C14+July!C14+June!C14+May!C14+April!C14+March!C14+February!C14+January!C14 -> 3300 | D14: =December!D14+November!D14+October!D14+September!D14+August!D14+July!D14+June!D14+May!D14+April!D14+March!D14+February!D14+January!D14 -> 3300 | E14: =C14-D14 -> 0 | F14: =D14/D32 -> 0.047413793
B15: Electric/ Gas | C15: =December!C15+November!C15+October!C15+September!C15+August!C15+July!C15+June!C15+May!C15+April!C15+March!C15+February!C15+January!C15 -> 2100 | D15: =December!D15+November!D15+October!D15+September!D15+August!D15+July!D15+June!D15+May!D15+April!D15+March!D15+February!D15+January!D15 -> 936 | E15: =C15-D15 -> 1164 | F15: =D15/D32 -> 0.013448276
B16: Water/ Seewer/ Trash | C16: =December!C16+November!C16+October!C16+September!C16+August!C16+July!C16+June!C16+May!C16+April!C16+March!C16+February!C16+January!C16 -> 624 | D16: =December!D16+November!D16+October!D16+September!D16+August!D16+July!D16+June!D16+May!D16+April!D16+March!D16+February!D16+January!D16 -> 648 | E16: =C16-D16 -> -24 | F16: =D16/D32 -> 0.0093103448
B17: Cable TV | C17: =December!C17+November!C17+October!C17+September!C17+August!C17+July!C17+June!C17+May!C17+April!C17+March!C17+February!C17+January!C17 -> 1380 | D17: =December!D17+November!D17+October!D17+September!D17+August!D17+July!D17+June!D17+May!D17+April!D17+March!D17+February!D17+January!D17 -> 1380 | E17: =C17-D17 -> 0 | F17: =D17/D32 -> 0.019827586
B18: Tuition | C18: =December!C18+November!C18+October!C18+September!C18+August!C18+July!C18+June!C18+May!C18+April!C18+March!C18+February!C18+January!C18 -> 6000 | D18: =December!D18+November!D18+October!D18+September!D18+August!D18+July!D18+June!D18+May!D18+April!D18+March!D18+February!D18+January!D18 -> 5700 | E18: =C18-D18 -> 300 | F18: =D18/D32 -> 0.081896552
B19: Internet | C19: =December!C19+November!C19+October!C19+September!C19+August!C19+July!C19+June!C19+May!C19+April!C19+March!C19+February!C19+January!C19 -> 720 | D19: =December!D19+November!D19+October!D19+September!D19+August!D19+July!D19+June!D19+May!D19+April!D19+March!D19+February!D19+January!D19 -> 720 | E19: =C19-D19 -> 0 | F19: =D19/D32 -> 0.010344828
B20: Maintenance/ Repairs | C20: =December!C20+November!C20+October!C20+September!C20+August!C20+July!C20+June!C20+May!C20+April!C20+March!C20+February!C20+January!C20 -> 0 | D20: =December!D20+November!D20+October!D20+September!D20+August!D20+July!D20+June!D20+May!D20+April!D20+March!D20+February!D20+January!D20 -> 300 | E20: =C20-D20 -> -300 | F20: =D20/D32 -> 0.0043103448
B21: Dining Out | C21: =December!C21+November!C21+October!C21+September!C21+August!C21+July!C21+June!C21+May!C21+April!C21+March!C21+February!C21+January!C21 -> 2400 | D21: =December!D21+November!D21+October!D21+September!D21+August!D21+July!D21+June!D21+May!D21+April!D21+March!D21+February!D21+January!D21 -> 2520 | E21: =C21-D21 -> -120 | F21: =D21/D32 -> 0.036206897
B22: Pets | C22: =December!C22+November!C22+October!C22+September!C22+August!C22+July!C22+June!C22+May!C22+April!C22+March!C22+February!C22+January!C22 -> 600 | D22: =December!D22+November!D22+October!D22+September!D22+August!D22+July!D22+June!D22+May!D22+April!D22+March!D22+February!D22+January!D22 -> 960 | E22: =C22-D22 -> -360 | F22: =D22/D32 -> 0.013793103
B23: Trasnportaion | C23: =December!C23+November!C23+October!C23+September!C23+August!C23+July!C23+June!C23+May!C23+April!C23+March!C23+February!C23+January!C23 -> 3600 | D23: =December!D23+November!D23+October!D23+September!D23+August!D23+July!D23+June!D23+May!D23+April!D23+March!D23+February!D23+January!D23 -> 3120 | E23: =C23-D23 -> 480 | F23: =D23/D32 -> 0.044827586
B24: Personal Care | C24: =December!C24+November!C24+October!C24+September!C24+August!C24+July!C24+June!C24+May!C24+April!C24+March!C24+February!C24+January!C24 -> 960 | D24: =December!D24+November!D24+October!D24+September!D24+August!D24+July!D24+June!D24+May!D24+April!D24+March!D24+February!D24+January!D24 -> 780 | E24: =C24-D24 -> 180 | F24: =D24/D32 -> 0.011206897
B25: Insurance | C25: =December!C25+November!C25+October!C25+September!C25+August!C25+July!C25+June!C25+May!C25+April!C25+March!C25+February!C25+January!C25 -> 2100 | D25: =December!D25+November!D25+October!D25+September!D25+August!D25+July!D25+June!D25+May!D25+April!D25+March!D25+February!D25+January!D25 -> 3060 | E25: =C25-D25 -> -960 | F25: =D25/D32 -> 0.043965517
B26: Credit Cards | C26: =December!C26+November!C26+October!C26+September!C26+August!C26+July!C26+June!C26+May!C26+April!C26+March!C26+February!C26+January!C26 -> 5100 | D26: =December!D26+November!D26+October!D26+September!D26+August!D26+July!D26+June!D26+May!D26+April!D26+March!D26+February!D26+January!D26 -> 6900 | E26: =C26-D26 -> -1800 | F26: =D26/D32 -> 0.099137931
B27: Loans | C27: =December!C27+November!C27+October!C27+September!C27+August!C27+July!C27+June!C27+May!C27+April!C27+March!C27+February!C27+January!C27 -> 0 | D27: =December!D27+November!D27+October!D27+September!D27+August!D27+July!D27+June!D27+May!D27+April!D27+March!D27+February!D27+January!D27 -> 0 | E27: =C27-D27 -> 0 | F27: =D27/D32 -> 0
B28: Taxes | C28: =December!C28+November!C28+October!C28+September!C28+August!C28+July!C28+June!C28+May!C28+April!C28+March!C28+February!C28+January!C28 -> 0 | D28: =December!D28+November!D28+October!D28+September!D28+August!D28+July!D28+June!D28+May!D28+April!D28+March!D28+February!D28+January!D28 -> 4200 | E28: =C28-D28 -> -4200 | F28: =D28/D32 -> 0.060344828
B29: Gifts/ Charity | C29: =December!C29+November!C29+October!C29+September!C29+August!C29+July!C29+June!C29+May!C29+April!C29+March!C29+February!C29+January!C29 -> 900 | D29: =December!D29+November!D29+October!D29+September!D29+August!D29+July!D29+June!D29+May!D29+April!D29+March!D29+February!D29+January!D29 -> 1500 | E29: =C29-D29 -> -600 | F29: =D29/D32 -> 0.021551724
B30: Savings | C30: =December!C30+November!C30+October!C30+September!C30+August!C30+July!C30+June!C30+May!C30+April!C30+March!C30+February!C30+January!C30 -> 11400 | D30: =December!D30+November!D30+October!D30+September!D30+August!D30+July!D30+June!D30+May!D30+April!D30+March!D30+February!D30+January!D30 -> 8832 | E30: =C30-D30 -> 2568 | F30: =D30/D32 -> 0.12689655
B31: Other | C31: =December!C31+November!C31+October!C31+September!C31+August!C31+July!C31+June!C31+May!C31+April!C31+March!C31+February!C31+January!C31 -> 216 | D31: =December!D31+November!D31+October!D31+September!D31+August!D31+July!D31+June!D31+May!D31+April!D31+March!D31+February!D31+January!D31 -> 0 | E31: =C31-D31 -> 216 | F31: =D31/D32 -> 0
B32: Total | C32: =SUM(C12:C31) -> 66000 | D32: =SUM(D12:D31) -> 69600 | E32: =C32-D32 -> -3600 | F32: =SUM(F12:F31) -> 1
